ClassicUserAccounts/__init__.py
ClassicUserAccounts/admin.py
ClassicUserAccounts/apps.py
ClassicUserAccounts/initial_migrations.py
ClassicUserAccounts/managers.py
ClassicUserAccounts/models.py
ClassicUserAccounts/urls.py
ClassicUserAccounts/views.py
ClassicUserAccounts/forms/__init__.py
ClassicUserAccounts/forms/forms.py
ClassicUserAccounts/middleware/ClassUserAccounts.py
ClassicUserAccounts/middleware/__init__.py
ClassicUserAccounts/migrations/0001_initial.py
ClassicUserAccounts/migrations/0002_auto_20180923_1213.py
ClassicUserAccounts/migrations/0003_user_user_code.py
ClassicUserAccounts/migrations/0010_role.py
ClassicUserAccounts/migrations/__init__.py
ClassicUserAccounts/miscellaneous/country.csv
ClassicUserAccounts/miscellaneous/database.sql
ClassicUserAccounts/miscellaneous/readme.txt
ClassicUserAccounts/miscellaneous/timezone.csv
ClassicUserAccounts/miscellaneous/zone.csv
ClassicUserAccounts/static/avatar_a.png
ClassicUserAccounts/static/avatar_f.png
ClassicUserAccounts/static/avatar_m.png
ClassicUserAccounts/static/css/AdminLTE.css
ClassicUserAccounts/static/css/AdminLTE.min.css
ClassicUserAccounts/static/css/site_account_base.css
ClassicUserAccounts/static/css/Ionicons/.bower.json
ClassicUserAccounts/static/css/Ionicons/css/ionicons.css
ClassicUserAccounts/static/css/Ionicons/css/ionicons.min.css
ClassicUserAccounts/static/css/Ionicons/fonts/ionicons.eot
ClassicUserAccounts/static/css/Ionicons/fonts/ionicons.svg
ClassicUserAccounts/static/css/Ionicons/fonts/ionicons.ttf
ClassicUserAccounts/static/css/Ionicons/fonts/ionicons.woff
ClassicUserAccounts/static/css/Ionicons/less/_ionicons-font.less
ClassicUserAccounts/static/css/Ionicons/less/_ionicons-icons.less
ClassicUserAccounts/static/css/Ionicons/less/_ionicons-variables.less
ClassicUserAccounts/static/css/Ionicons/less/ionicons.less
ClassicUserAccounts/static/css/Ionicons/png/512/alert-circled.png
ClassicUserAccounts/static/css/Ionicons/png/512/alert.png
django_classic_user_accounts-1.0.12.dist-info/METADATA
django_classic_user_accounts-1.0.12.dist-info/RECORD
django_classic_user_accounts-1.0.12.dist-info/WHEEL
django_classic_user_accounts-1.0.12.dist-info/top_level.txt
